esperanza/__init__.py
esperanza/algorithm.py
esperanza/app.py
esperanza/applogger.py
esperanza/batch.py
esperanza/parser.py
esperanza/test.py
esperanza/utils.py
esperanza-0.0.1.dist-info/licenses/LICENSE
esperanza-0.0.1.dist-info/METADATA
esperanza-0.0.1.dist-info/WHEEL
esperanza-0.0.1.dist-info/entry_points.txt
esperanza-0.0.1.dist-info/top_level.txt
esperanza-0.0.1.dist-info/RECORD
